[
  {
    "label": "IndianRed",
    "value": "IndianRed"
  },
  {
    "label": "LightCoral",
    "value": "LightCoral"
  },
  {
    "label": "Salmon",
    "value": "Salmon"
  },
  {
    "label": "DarkSalmon",
    "value": "DarkSalmon"
  },
  {
    "label": "LightSalmon",
    "value": "LightSalmon"
  },
  {
    "label": "Crimson",
    "value": "Crimson"
  },
  {
    "label": "Red",
    "value": "Red"
  },
  {
    "label": "FireBrick",
    "value": "FireBrick"
  },
  {
    "label": "DarkRed",
    "value": "DarkRed"
  }
]
